{
 "id": "5a9373e1-bb3e-4e06-889d-8760ab5a676e",
 "type": "root_container",
 "Data": {
  "Line": 0,
  "Contest": "",
  "Info": ""
 },
 "children": [
  {
   "id": "9f4de9fd-9993-48a4-8d20-a6b6b46bd82d",
   "type": "",
   "Data": {
    "Line": 0,
    "Contest": "run",
    "Info": "run code"
   },
   "Columns": null,
   "PreventUserColumnResize": false
  },
  {
   "id": "f5b134d1-b5e0-4495-823c-7de96b8d391c",
   "type": "",
   "Data": {
    "Line": 1,
    "Contest": "run",
    "Info": "run code"
   },
   "Columns": null,
   "PreventUserColumnResize": false
  },
  {
   "id": "cc05f7b8-e42c-4228-98ba-57ef282b0d74",
   "type": "",
   "Data": {
    "Line": 2,
    "Contest": "run",
    "Info": "run code"
   },
   "Columns": null,
   "PreventUserColumnResize": false
  },
  {
   "id": "125c9f32-4aef-4432-8ede-8ebefe49f87b",
   "type": "",
   "Data": {
    "Line": 3,
    "Contest": "run",
    "Info": "run code"
   },
   "Columns": null,
   "PreventUserColumnResize": false
  },
  {
   "id": "86017f96-001d-4d51-84a6-ff0c7139c345",
   "type": "",
   "Data": {
    "Line": 4,
    "Contest": "run",
    "Info": "run code"
   },
   "Columns": null,
   "PreventUserColumnResize": false
  },
  {
   "id": "32f98c4d-9866-498a-a5f6-063858124f23",
   "type": "",
   "Data": {
    "Line": 5,
    "Contest": "run",
    "Info": "run code"
   },
   "Columns": null,
   "PreventUserColumnResize": false
  },
  {
   "id": "201d549b-373f-4075-b080-d823696f24d0",
   "type": "",
   "Data": {
    "Line": 6,
    "Contest": "run",
    "Info": "run code"
   },
   "Columns": null,
   "PreventUserColumnResize": false
  },
  {
   "id": "d66379d4-3a3b-4086-a0e2-a5164ac8cc8f",
   "type": "",
   "Data": {
    "Line": 7,
    "Contest": "run",
    "Info": "run code"
   },
   "Columns": null,
   "PreventUserColumnResize": false
  },
  {
   "id": "dbf3eb5b-af27-4625-a8d8-464be637e99c",
   "type": "",
   "Data": {
    "Line": 8,
    "Contest": "run",
    "Info": "run code"
   },
   "Columns": null,
   "PreventUserColumnResize": false
  },
  {
   "id": "7d0cecb6-98ba-45fb-a85c-a90e445ca9f3",
   "type": "",
   "Data": {
    "Line": 9,
    "Contest": "run",
    "Info": "run code"
   },
   "Columns": null,
   "PreventUserColumnResize": false
  },
  {
   "id": "df8788dc-4e84-4015-9489-201d0db84412",
   "type": "",
   "Data": {
    "Line": 10,
    "Contest": "run",
    "Info": "run code"
   },
   "Columns": null,
   "PreventUserColumnResize": false
  },
  {
   "id": "c890d13e-7d82-4519-9c87-b9dd63fea7e7",
   "type": "",
   "Data": {
    "Line": 11,
    "Contest": "run",
    "Info": "run code"
   },
   "Columns": null,
   "PreventUserColumnResize": false
  },
  {
   "id": "0ef55600-70b8-46f4-a289-5cdd94d0f3f7",
   "type": "",
   "Data": {
    "Line": 12,
    "Contest": "run",
    "Info": "run code"
   },
   "Columns": null,
   "PreventUserColumnResize": false
  },
  {
   "id": "7e889396-8b7b-4bcb-9b59-7f49e20112f5",
   "type": "",
   "Data": {
    "Line": 13,
    "Contest": "run",
    "Info": "run code"
   },
   "Columns": null,
   "PreventUserColumnResize": false
  },
  {
   "id": "b69dba7f-20d6-4f6e-946e-569a5a9128fe",
   "type": "",
   "Data": {
    "Line": 14,
    "Contest": "run",
    "Info": "run code"
   },
   "Columns": null,
   "PreventUserColumnResize": false
  },
  {
   "id": "c3dc7927-56af-4301-a24e-e806559e8f58",
   "type": "",
   "Data": {
    "Line": 15,
    "Contest": "run",
    "Info": "run code"
   },
   "Columns": null,
   "PreventUserColumnResize": false
  },
  {
   "id": "375136f7-a659-4408-9002-ea260c81df77",
   "type": "",
   "Data": {
    "Line": 16,
    "Contest": "run",
    "Info": "run code"
   },
   "Columns": null,
   "PreventUserColumnResize": false
  },
  {
   "id": "5aac2341-8dc6-44bd-96ab-9c8be9563dd6",
   "type": "",
   "Data": {
    "Line": 17,
    "Contest": "run",
    "Info": "run code"
   },
   "Columns": null,
   "PreventUserColumnResize": false
  },
  {
   "id": "4800d824-9a1b-4ec5-9c68-5ec38666c859",
   "type": "",
   "Data": {
    "Line": 18,
    "Contest": "run",
    "Info": "run code"
   },
   "Columns": null,
   "PreventUserColumnResize": false
  },
  {
   "id": "3645f04d-65e8-41ba-b11a-cd890df2573d",
   "type": "",
   "Data": {
    "Line": 19,
    "Contest": "run",
    "Info": "run code"
   },
   "Columns": null,
   "PreventUserColumnResize": false
  },
  {
   "id": "64454df0-c59a-4aff-89a3-e3c0c1893f36",
   "type": "",
   "Data": {
    "Line": 20,
    "Contest": "run",
    "Info": "run code"
   },
   "Columns": null,
   "PreventUserColumnResize": false
  },
  {
   "id": "a44541ab-b0d6-4e64-b849-39d256b2c705",
   "type": "",
   "Data": {
    "Line": 21,
    "Contest": "run",
    "Info": "run code"
   },
   "Columns": null,
   "PreventUserColumnResize": false
  },
  {
   "id": "96ec959d-916f-4c14-941f-f3898fdd3d6e",
   "type": "",
   "Data": {
    "Line": 22,
    "Contest": "run",
    "Info": "run code"
   },
   "Columns": null,
   "PreventUserColumnResize": false
  },
  {
   "id": "65d10ba1-fe81-4d31-abda-81f433c54416",
   "type": "",
   "Data": {
    "Line": 23,
    "Contest": "run",
    "Info": "run code"
   },
   "Columns": null,
   "PreventUserColumnResize": false
  },
  {
   "id": "391e7c6b-c834-4645-940a-f444b68ce215",
   "type": "",
   "Data": {
    "Line": 24,
    "Contest": "run",
    "Info": "run code"
   },
   "Columns": null,
   "PreventUserColumnResize": false
  },
  {
   "id": "33fcc31b-a8d3-4460-ac82-031603286bc4",
   "type": "",
   "Data": {
    "Line": 25,
    "Contest": "run",
    "Info": "run code"
   },
   "Columns": null,
   "PreventUserColumnResize": false
  },
  {
   "id": "70bf0d84-220d-4ac5-8a1c-45ceccd1430b",
   "type": "",
   "Data": {
    "Line": 26,
    "Contest": "run",
    "Info": "run code"
   },
   "Columns": null,
   "PreventUserColumnResize": false
  },
  {
   "id": "4a41cddc-afab-4f10-bd36-2a7cca8aa903",
   "type": "",
   "Data": {
    "Line": 27,
    "Contest": "run",
    "Info": "run code"
   },
   "Columns": null,
   "PreventUserColumnResize": false
  },
  {
   "id": "2373a17a-427a-4354-bc00-958795187b0d",
   "type": "",
   "Data": {
    "Line": 28,
    "Contest": "run",
    "Info": "run code"
   },
   "Columns": null,
   "PreventUserColumnResize": false
  },
  {
   "id": "9d1cec50-763b-4bae-b75d-b529f3448f0d",
   "type": "",
   "Data": {
    "Line": 29,
    "Contest": "run",
    "Info": "run code"
   },
   "Columns": null,
   "PreventUserColumnResize": false
  },
  {
   "id": "6584f6ad-15c9-4ca7-bf6c-98d7f5a29fc7",
   "type": "",
   "Data": {
    "Line": 30,
    "Contest": "run",
    "Info": "run code"
   },
   "Columns": null,
   "PreventUserColumnResize": false
  },
  {
   "id": "b9769f73-9752-4f43-83b3-3f080d2ee2aa",
   "type": "",
   "Data": {
    "Line": 31,
    "Contest": "run",
    "Info": "run code"
   },
   "Columns": null,
   "PreventUserColumnResize": false
  },
  {
   "id": "9e4af66c-0800-4a32-bb60-c04e78d07a62",
   "type": "",
   "Data": {
    "Line": 32,
    "Contest": "run",
    "Info": "run code"
   },
   "Columns": null,
   "PreventUserColumnResize": false
  },
  {
   "id": "264d8c9c-58fd-4dc3-8cfa-4f09fa8654a4",
   "type": "",
   "Data": {
    "Line": 33,
    "Contest": "run",
    "Info": "run code"
   },
   "Columns": null,
   "PreventUserColumnResize": false
  },
  {
   "id": "678dbd91-9c14-4f96-886d-c4dda281ee01",
   "type": "",
   "Data": {
    "Line": 34,
    "Contest": "run",
    "Info": "run code"
   },
   "Columns": null,
   "PreventUserColumnResize": false
  },
  {
   "id": "c699e17c-a5f5-4a98-b22a-be47d3e83983",
   "type": "",
   "Data": {
    "Line": 35,
    "Contest": "run",
    "Info": "run code"
   },
   "Columns": null,
   "PreventUserColumnResize": false
  },
  {
   "id": "f29be604-bf86-4ee6-8b31-f382a1b60d8e",
   "type": "",
   "Data": {
    "Line": 36,
    "Contest": "run",
    "Info": "run code"
   },
   "Columns": null,
   "PreventUserColumnResize": false
  },
  {
   "id": "762ab166-2e0b-4ccf-bdfe-8348cbff209f",
   "type": "",
   "Data": {
    "Line": 37,
    "Contest": "run",
    "Info": "run code"
   },
   "Columns": null,
   "PreventUserColumnResize": false
  },
  {
   "id": "5783fb64-b518-4e3d-887f-adc7804e7345",
   "type": "",
   "Data": {
    "Line": 38,
    "Contest": "run",
    "Info": "run code"
   },
   "Columns": null,
   "PreventUserColumnResize": false
  },
  {
   "id": "aa72b5e3-0494-4f55-afa8-38f7ed3938f2",
   "type": "",
   "Data": {
    "Line": 39,
    "Contest": "run",
    "Info": "run code"
   },
   "Columns": null,
   "PreventUserColumnResize": false
  },
  {
   "id": "df1468f3-28d8-4d20-96e4-338e1641b7c0",
   "type": "",
   "Data": {
    "Line": 40,
    "Contest": "run",
    "Info": "run code"
   },
   "Columns": null,
   "PreventUserColumnResize": false
  },
  {
   "id": "7488edc4-6098-4150-a37a-8029daf5495b",
   "type": "",
   "Data": {
    "Line": 41,
    "Contest": "run",
    "Info": "run code"
   },
   "Columns": null,
   "PreventUserColumnResize": false
  },
  {
   "id": "bedb098b-ba38-41c4-951c-e6e03d0ebce2",
   "type": "",
   "Data": {
    "Line": 42,
    "Contest": "run",
    "Info": "run code"
   },
   "Columns": null,
   "PreventUserColumnResize": false
  },
  {
   "id": "74521971-6d92-43c9-ac9d-5739a975a801",
   "type": "",
   "Data": {
    "Line": 43,
    "Contest": "run",
    "Info": "run code"
   },
   "Columns": null,
   "PreventUserColumnResize": false
  },
  {
   "id": "15c7b00c-fc71-4ae9-9d60-1d3bff8bccf7",
   "type": "",
   "Data": {
    "Line": 44,
    "Contest": "run",
    "Info": "run code"
   },
   "Columns": null,
   "PreventUserColumnResize": false
  },
  {
   "id": "f97684bd-48f9-4caf-b9ce-8cc91006649b",
   "type": "",
   "Data": {
    "Line": 45,
    "Contest": "run",
    "Info": "run code"
   },
   "Columns": null,
   "PreventUserColumnResize": false
  },
  {
   "id": "9b29f99d-da50-4fc8-adcc-612a53b5abca",
   "type": "",
   "Data": {
    "Line": 46,
    "Contest": "run",
    "Info": "run code"
   },
   "Columns": null,
   "PreventUserColumnResize": false
  },
  {
   "id": "1dc421a7-b0ae-4b09-a10a-d6a7b8a314c3",
   "type": "",
   "Data": {
    "Line": 47,
    "Contest": "run",
    "Info": "run code"
   },
   "Columns": null,
   "PreventUserColumnResize": false
  },
  {
   "id": "78cc345d-771e-4330-97ca-6ef5b2d70f7d",
   "type": "",
   "Data": {
    "Line": 48,
    "Contest": "run",
    "Info": "run code"
   },
   "Columns": null,
   "PreventUserColumnResize": false
  },
  {
   "id": "b2ef1646-10a4-4d13-8e74-5e4f528ce68c",
   "type": "",
   "Data": {
    "Line": 49,
    "Contest": "run",
    "Info": "run code"
   },
   "Columns": null,
   "PreventUserColumnResize": false
  },
  {
   "id": "ff4f0953-f287-4f9e-8a08-751dca251cc8",
   "type": "",
   "Data": {
    "Line": 50,
    "Contest": "run",
    "Info": "run code"
   },
   "Columns": null,
   "PreventUserColumnResize": false
  },
  {
   "id": "82ca31ff-794d-4469-b4e2-4e65dc7be21e",
   "type": "",
   "Data": {
    "Line": 51,
    "Contest": "run",
    "Info": "run code"
   },
   "Columns": null,
   "PreventUserColumnResize": false
  },
  {
   "id": "c6bcdc4b-882d-4f18-b9bb-b29570d03edc",
   "type": "",
   "Data": {
    "Line": 52,
    "Contest": "run",
    "Info": "run code"
   },
   "Columns": null,
   "PreventUserColumnResize": false
  },
  {
   "id": "a1b4a6ed-fc6b-4851-9480-7c537550bec8",
   "type": "",
   "Data": {
    "Line": 53,
    "Contest": "run",
    "Info": "run code"
   },
   "Columns": null,
   "PreventUserColumnResize": false
  },
  {
   "id": "c1157a0f-a8e0-4f41-b21b-a7e4ce86ee12",
   "type": "",
   "Data": {
    "Line": 54,
    "Contest": "run",
    "Info": "run code"
   },
   "Columns": null,
   "PreventUserColumnResize": false
  },
  {
   "id": "0ca18ee5-d160-436c-a2de-f971c67ac10b",
   "type": "",
   "Data": {
    "Line": 55,
    "Contest": "run",
    "Info": "run code"
   },
   "Columns": null,
   "PreventUserColumnResize": false
  },
  {
   "id": "81ddab9d-0647-41b7-a313-f38abac379b0",
   "type": "",
   "Data": {
    "Line": 56,
    "Contest": "run",
    "Info": "run code"
   },
   "Columns": null,
   "PreventUserColumnResize": false
  },
  {
   "id": "cff35654-6c24-49ef-971c-f5d03874b929",
   "type": "",
   "Data": {
    "Line": 57,
    "Contest": "run",
    "Info": "run code"
   },
   "Columns": null,
   "PreventUserColumnResize": false
  },
  {
   "id": "faf5c7fa-fb47-4b80-8f60-dc27721e18c0",
   "type": "",
   "Data": {
    "Line": 58,
    "Contest": "run",
    "Info": "run code"
   },
   "Columns": null,
   "PreventUserColumnResize": false
  },
  {
   "id": "52f4a6ac-457a-4e5c-a993-0986cb33e797",
   "type": "",
   "Data": {
    "Line": 59,
    "Contest": "run",
    "Info": "run code"
   },
   "Columns": null,
   "PreventUserColumnResize": false
  },
  {
   "id": "ef2aa662-559b-4dd8-ac2a-3df785b54487",
   "type": "",
   "Data": {
    "Line": 60,
    "Contest": "run",
    "Info": "run code"
   },
   "Columns": null,
   "PreventUserColumnResize": false
  },
  {
   "id": "c25518fa-7c68-4d0d-aa96-36c4258eacc9",
   "type": "",
   "Data": {
    "Line": 61,
    "Contest": "run",
    "Info": "run code"
   },
   "Columns": null,
   "PreventUserColumnResize": false
  },
  {
   "id": "e6db5949-b77c-449a-b7aa-25d3ba8fc35c",
   "type": "",
   "Data": {
    "Line": 62,
    "Contest": "run",
    "Info": "run code"
   },
   "Columns": null,
   "PreventUserColumnResize": false
  },
  {
   "id": "0cf84e3f-d07b-4dc4-91d3-036866bf7712",
   "type": "",
   "Data": {
    "Line": 63,
    "Contest": "run",
    "Info": "run code"
   },
   "Columns": null,
   "PreventUserColumnResize": false
  },
  {
   "id": "0b98bc80-7387-42ce-92f6-02d3055aff06",
   "type": "",
   "Data": {
    "Line": 64,
    "Contest": "run",
    "Info": "run code"
   },
   "Columns": null,
   "PreventUserColumnResize": false
  },
  {
   "id": "81c59e7e-d39d-43e9-8791-2280a7066a95",
   "type": "",
   "Data": {
    "Line": 65,
    "Contest": "run",
    "Info": "run code"
   },
   "Columns": null,
   "PreventUserColumnResize": false
  },
  {
   "id": "af7a5eac-e4d6-4693-a124-c8ae32f095a3",
   "type": "",
   "Data": {
    "Line": 66,
    "Contest": "run",
    "Info": "run code"
   },
   "Columns": null,
   "PreventUserColumnResize": false
  },
  {
   "id": "a3475ced-8790-426f-bbbc-1314d89a7cdd",
   "type": "",
   "Data": {
    "Line": 67,
    "Contest": "run",
    "Info": "run code"
   },
   "Columns": null,
   "PreventUserColumnResize": false
  },
  {
   "id": "7dfea201-8d0d-4073-8800-41ea33561ec4",
   "type": "",
   "Data": {
    "Line": 68,
    "Contest": "run",
    "Info": "run code"
   },
   "Columns": null,
   "PreventUserColumnResize": false
  },
  {
   "id": "51f6e253-35ee-4442-89f7-e93f1dc37fdf",
   "type": "",
   "Data": {
    "Line": 69,
    "Contest": "run",
    "Info": "run code"
   },
   "Columns": null,
   "PreventUserColumnResize": false
  },
  {
   "id": "6d479e02-7ac9-4c13-a074-f4214fa72a8b",
   "type": "",
   "Data": {
    "Line": 70,
    "Contest": "run",
    "Info": "run code"
   },
   "Columns": null,
   "PreventUserColumnResize": false
  },
  {
   "id": "c3462e10-72c1-48be-aa43-910d3502df3d",
   "type": "",
   "Data": {
    "Line": 71,
    "Contest": "run",
    "Info": "run code"
   },
   "Columns": null,
   "PreventUserColumnResize": false
  },
  {
   "id": "65f0e9e4-0519-4b83-a089-619cc7f0785f",
   "type": "",
   "Data": {
    "Line": 72,
    "Contest": "run",
    "Info": "run code"
   },
   "Columns": null,
   "PreventUserColumnResize": false
  },
  {
   "id": "b479a81e-6a16-4388-801d-a8800d09a465",
   "type": "",
   "Data": {
    "Line": 73,
    "Contest": "run",
    "Info": "run code"
   },
   "Columns": null,
   "PreventUserColumnResize": false
  },
  {
   "id": "90e8b0c0-0621-4a42-b663-925f3e2c44e0",
   "type": "",
   "Data": {
    "Line": 74,
    "Contest": "run",
    "Info": "run code"
   },
   "Columns": null,
   "PreventUserColumnResize": false
  },
  {
   "id": "c28f2712-43f2-402a-8988-077adfada07d",
   "type": "",
   "Data": {
    "Line": 75,
    "Contest": "run",
    "Info": "run code"
   },
   "Columns": null,
   "PreventUserColumnResize": false
  },
  {
   "id": "4595cad0-0dc9-47c3-8a31-a6c6185f29bd",
   "type": "",
   "Data": {
    "Line": 76,
    "Contest": "run",
    "Info": "run code"
   },
   "Columns": null,
   "PreventUserColumnResize": false
  },
  {
   "id": "41fa0b48-8912-465b-881b-a79aae7bd519",
   "type": "",
   "Data": {
    "Line": 77,
    "Contest": "run",
    "Info": "run code"
   },
   "Columns": null,
   "PreventUserColumnResize": false
  },
  {
   "id": "ec03bd5f-02dc-4202-80f1-62cde978653c",
   "type": "",
   "Data": {
    "Line": 78,
    "Contest": "run",
    "Info": "run code"
   },
   "Columns": null,
   "PreventUserColumnResize": false
  },
  {
   "id": "7ae7ba23-c01a-4c2c-85cd-be8e915328c4",
   "type": "",
   "Data": {
    "Line": 79,
    "Contest": "run",
    "Info": "run code"
   },
   "Columns": null,
   "PreventUserColumnResize": false
  },
  {
   "id": "96919127-4519-47d0-a6a3-83cc221d0146",
   "type": "",
   "Data": {
    "Line": 80,
    "Contest": "run",
    "Info": "run code"
   },
   "Columns": null,
   "PreventUserColumnResize": false
  },
  {
   "id": "e033628c-0416-453d-b7b1-b61487a98c8d",
   "type": "",
   "Data": {
    "Line": 81,
    "Contest": "run",
    "Info": "run code"
   },
   "Columns": null,
   "PreventUserColumnResize": false
  },
  {
   "id": "733a04b0-387a-4e2d-933d-386d02e856db",
   "type": "",
   "Data": {
    "Line": 82,
    "Contest": "run",
    "Info": "run code"
   },
   "Columns": null,
   "PreventUserColumnResize": false
  },
  {
   "id": "a18440aa-4ec0-4157-851f-ebd679083fda",
   "type": "",
   "Data": {
    "Line": 83,
    "Contest": "run",
    "Info": "run code"
   },
   "Columns": null,
   "PreventUserColumnResize": false
  },
  {
   "id": "78dc8b2a-1f7a-45df-83c5-b08756d09367",
   "type": "",
   "Data": {
    "Line": 84,
    "Contest": "run",
    "Info": "run code"
   },
   "Columns": null,
   "PreventUserColumnResize": false
  },
  {
   "id": "08e444d0-bb3c-4329-b52f-e984dc85a37b",
   "type": "",
   "Data": {
    "Line": 85,
    "Contest": "run",
    "Info": "run code"
   },
   "Columns": null,
   "PreventUserColumnResize": false
  },
  {
   "id": "422a2658-96b4-47a1-8bba-bd82ae153089",
   "type": "",
   "Data": {
    "Line": 86,
    "Contest": "run",
    "Info": "run code"
   },
   "Columns": null,
   "PreventUserColumnResize": false
  },
  {
   "id": "95c0fa67-14f0-46c4-95b9-955ce4011a5b",
   "type": "",
   "Data": {
    "Line": 87,
    "Contest": "run",
    "Info": "run code"
   },
   "Columns": null,
   "PreventUserColumnResize": false
  },
  {
   "id": "803dab19-46b8-4d68-bdce-1db880547458",
   "type": "",
   "Data": {
    "Line": 88,
    "Contest": "run",
    "Info": "run code"
   },
   "Columns": null,
   "PreventUserColumnResize": false
  },
  {
   "id": "fe46f51a-506e-4f09-9209-38692f8783c8",
   "type": "",
   "Data": {
    "Line": 89,
    "Contest": "run",
    "Info": "run code"
   },
   "Columns": null,
   "PreventUserColumnResize": false
  },
  {
   "id": "d805801a-cd2f-4e45-968a-da0f3ace7467",
   "type": "",
   "Data": {
    "Line": 90,
    "Contest": "run",
    "Info": "run code"
   },
   "Columns": null,
   "PreventUserColumnResize": false
  },
  {
   "id": "339da64e-13e5-4992-9b70-50d99002a035",
   "type": "",
   "Data": {
    "Line": 91,
    "Contest": "run",
    "Info": "run code"
   },
   "Columns": null,
   "PreventUserColumnResize": false
  },
  {
   "id": "e89a6896-35c7-4734-8602-ee6244892998",
   "type": "",
   "Data": {
    "Line": 92,
    "Contest": "run",
    "Info": "run code"
   },
   "Columns": null,
   "PreventUserColumnResize": false
  },
  {
   "id": "cff41115-7780-466e-b4fa-4ba8bf2b5504",
   "type": "",
   "Data": {
    "Line": 93,
    "Contest": "run",
    "Info": "run code"
   },
   "Columns": null,
   "PreventUserColumnResize": false
  },
  {
   "id": "fceee24b-8a50-463c-840d-c079da53ee74",
   "type": "",
   "Data": {
    "Line": 94,
    "Contest": "run",
    "Info": "run code"
   },
   "Columns": null,
   "PreventUserColumnResize": false
  },
  {
   "id": "0fe96c13-8fe1-4543-b170-b9b683e899f5",
   "type": "",
   "Data": {
    "Line": 95,
    "Contest": "run",
    "Info": "run code"
   },
   "Columns": null,
   "PreventUserColumnResize": false
  },
  {
   "id": "63565a5d-9049-49e5-991d-a91aaa4ca9f2",
   "type": "",
   "Data": {
    "Line": 96,
    "Contest": "run",
    "Info": "run code"
   },
   "Columns": null,
   "PreventUserColumnResize": false
  },
  {
   "id": "f933d2a8-e85e-43a9-824b-7a834fe20a3d",
   "type": "",
   "Data": {
    "Line": 97,
    "Contest": "run",
    "Info": "run code"
   },
   "Columns": null,
   "PreventUserColumnResize": false
  },
  {
   "id": "b62f8e01-56f0-45fe-a72d-c6b6df190baf",
   "type": "",
   "Data": {
    "Line": 98,
    "Contest": "run",
    "Info": "run code"
   },
   "Columns": null,
   "PreventUserColumnResize": false
  },
  {
   "id": "2ae0bb48-de1c-4f2d-b2ba-b491f64d4ba4",
   "type": "",
   "Data": {
    "Line": 99,
    "Contest": "run",
    "Info": "run code"
   },
   "Columns": null,
   "PreventUserColumnResize": false
  }
 ],
 "Columns": [
  {
   "ID": 0,
   "Current": 44,
   "Minimum": 34.072266,
   "Maximum": 10000,
   "AutoMinimum": 0,
   "AutoMaximum": 0,
   "Cell": "Line"
  },
  {
   "ID": 1,
   "Current": 56.603516,
   "Minimum": 56.603516,
   "Maximum": 10000,
   "AutoMinimum": 0,
   "AutoMaximum": 0,
   "Cell": "Contest"
  },
  {
   "ID": 2,
   "Current": 63,
   "Minimum": 32.376953,
   "Maximum": 10000,
   "AutoMinimum": 0,
   "AutoMaximum": 0,
   "Cell": "Info"
  }
 ],
 "PreventUserColumnResize": false
}