{
 "id": "f91e393d-4a12-4964-8be7-1ed12a19ed1b",
 "type": "root_container",
 "Data": {
  "Line": 0,
  "Contest": "",
  "Info": ""
 },
 "children": [
  {
   "id": "41358c58-59ec-408c-84e0-822c6801e31c",
   "type": "",
   "Data": {
    "Line": 0,
    "Contest": "run",
    "Info": "run code"
   },
   "Columns": null,
   "PreventUserColumnResize": false
  },
  {
   "id": "1a4dfa37-b9c0-4643-93a1-0836e92571e9",
   "type": "",
   "Data": {
    "Line": 1,
    "Contest": "run",
    "Info": "run code"
   },
   "Columns": null,
   "PreventUserColumnResize": false
  },
  {
   "id": "fa518298-7178-4950-ac35-778e1c9c851b",
   "type": "",
   "Data": {
    "Line": 2,
    "Contest": "run",
    "Info": "run code"
   },
   "Columns": null,
   "PreventUserColumnResize": false
  },
  {
   "id": "0ac9a6a7-89cc-4f6e-909c-8f6b2190d5c3",
   "type": "",
   "Data": {
    "Line": 3,
    "Contest": "run",
    "Info": "run code"
   },
   "Columns": null,
   "PreventUserColumnResize": false
  },
  {
   "id": "1d31aafe-fdb8-4afa-9f4f-7af1d94e50e7",
   "type": "",
   "Data": {
    "Line": 4,
    "Contest": "run",
    "Info": "run code"
   },
   "Columns": null,
   "PreventUserColumnResize": false
  },
  {
   "id": "c144a19c-4736-41ef-b66c-49a9162a2179",
   "type": "",
   "Data": {
    "Line": 5,
    "Contest": "run",
    "Info": "run code"
   },
   "Columns": null,
   "PreventUserColumnResize": false
  },
  {
   "id": "cb974c64-f944-41dc-8dc2-519955384080",
   "type": "",
   "Data": {
    "Line": 6,
    "Contest": "run",
    "Info": "run code"
   },
   "Columns": null,
   "PreventUserColumnResize": false
  },
  {
   "id": "ab53c61b-930e-4115-a18e-75d8c40189de",
   "type": "",
   "Data": {
    "Line": 7,
    "Contest": "run",
    "Info": "run code"
   },
   "Columns": null,
   "PreventUserColumnResize": false
  },
  {
   "id": "3f01efae-1480-4707-a8f8-bee11979a7a3",
   "type": "",
   "Data": {
    "Line": 8,
    "Contest": "run",
    "Info": "run code"
   },
   "Columns": null,
   "PreventUserColumnResize": false
  },
  {
   "id": "3a9619eb-1b95-4b6b-a261-30ac54e6844f",
   "type": "",
   "Data": {
    "Line": 9,
    "Contest": "run",
    "Info": "run code"
   },
   "Columns": null,
   "PreventUserColumnResize": false
  },
  {
   "id": "02308c81-7398-45e8-8e44-fee8d751370a",
   "type": "",
   "Data": {
    "Line": 10,
    "Contest": "run",
    "Info": "run code"
   },
   "Columns": null,
   "PreventUserColumnResize": false
  },
  {
   "id": "33c807cd-8a4c-4948-b7de-1f55a5370c2e",
   "type": "",
   "Data": {
    "Line": 11,
    "Contest": "run",
    "Info": "run code"
   },
   "Columns": null,
   "PreventUserColumnResize": false
  },
  {
   "id": "35ca174e-4204-4669-adda-9904c118ea6a",
   "type": "",
   "Data": {
    "Line": 12,
    "Contest": "run",
    "Info": "run code"
   },
   "Columns": null,
   "PreventUserColumnResize": false
  },
  {
   "id": "bab8c4cb-49b0-4da0-b1aa-9740f8a7e0cb",
   "type": "",
   "Data": {
    "Line": 13,
    "Contest": "run",
    "Info": "run code"
   },
   "Columns": null,
   "PreventUserColumnResize": false
  },
  {
   "id": "f97640c5-0c77-4dfa-9b67-d619c52c74a9",
   "type": "",
   "Data": {
    "Line": 14,
    "Contest": "run",
    "Info": "run code"
   },
   "Columns": null,
   "PreventUserColumnResize": false
  },
  {
   "id": "5ae6ae4f-f321-42de-a2d1-71674d47c059",
   "type": "",
   "Data": {
    "Line": 15,
    "Contest": "run",
    "Info": "run code"
   },
   "Columns": null,
   "PreventUserColumnResize": false
  },
  {
   "id": "0ca2e311-9705-441c-9fd1-f715b494757e",
   "type": "",
   "Data": {
    "Line": 16,
    "Contest": "run",
    "Info": "run code"
   },
   "Columns": null,
   "PreventUserColumnResize": false
  },
  {
   "id": "0d061c06-e9bd-4d02-ad55-0d601aa32c3f",
   "type": "",
   "Data": {
    "Line": 17,
    "Contest": "run",
    "Info": "run code"
   },
   "Columns": null,
   "PreventUserColumnResize": false
  },
  {
   "id": "866d6c35-7944-4282-838b-9480d8b814ad",
   "type": "",
   "Data": {
    "Line": 18,
    "Contest": "run",
    "Info": "run code"
   },
   "Columns": null,
   "PreventUserColumnResize": false
  },
  {
   "id": "3cb39e12-bc5b-49e3-9da4-5ffb4ad664ac",
   "type": "",
   "Data": {
    "Line": 19,
    "Contest": "run",
    "Info": "run code"
   },
   "Columns": null,
   "PreventUserColumnResize": false
  },
  {
   "id": "e69ef225-960d-4838-b043-cbf9a03c63ac",
   "type": "",
   "Data": {
    "Line": 20,
    "Contest": "run",
    "Info": "run code"
   },
   "Columns": null,
   "PreventUserColumnResize": false
  },
  {
   "id": "1bed202b-85b4-4be1-b886-b2a65aa306c7",
   "type": "",
   "Data": {
    "Line": 21,
    "Contest": "run",
    "Info": "run code"
   },
   "Columns": null,
   "PreventUserColumnResize": false
  },
  {
   "id": "0c36e483-7400-49da-8f49-63332d7bb832",
   "type": "",
   "Data": {
    "Line": 22,
    "Contest": "run",
    "Info": "run code"
   },
   "Columns": null,
   "PreventUserColumnResize": false
  },
  {
   "id": "e0067f53-22de-45e6-9d70-afc24a927196",
   "type": "",
   "Data": {
    "Line": 23,
    "Contest": "run",
    "Info": "run code"
   },
   "Columns": null,
   "PreventUserColumnResize": false
  },
  {
   "id": "d319fa67-5c67-4a0a-9bc0-a089ef614502",
   "type": "",
   "Data": {
    "Line": 24,
    "Contest": "run",
    "Info": "run code"
   },
   "Columns": null,
   "PreventUserColumnResize": false
  },
  {
   "id": "fd3f6a8e-8fcf-4d68-a3f9-4cbb76ab42c8",
   "type": "",
   "Data": {
    "Line": 25,
    "Contest": "run",
    "Info": "run code"
   },
   "Columns": null,
   "PreventUserColumnResize": false
  },
  {
   "id": "5adec6d2-70f3-439e-8f2b-fced4b3f6391",
   "type": "",
   "Data": {
    "Line": 26,
    "Contest": "run",
    "Info": "run code"
   },
   "Columns": null,
   "PreventUserColumnResize": false
  },
  {
   "id": "ed813f57-eef9-4d1c-8dad-64a0157b6361",
   "type": "",
   "Data": {
    "Line": 27,
    "Contest": "run",
    "Info": "run code"
   },
   "Columns": null,
   "PreventUserColumnResize": false
  },
  {
   "id": "775c08a8-72e4-471b-8099-f28d7272a9a2",
   "type": "",
   "Data": {
    "Line": 28,
    "Contest": "run",
    "Info": "run code"
   },
   "Columns": null,
   "PreventUserColumnResize": false
  },
  {
   "id": "98098cdf-e2b0-461d-9645-15305d6e74b2",
   "type": "",
   "Data": {
    "Line": 29,
    "Contest": "run",
    "Info": "run code"
   },
   "Columns": null,
   "PreventUserColumnResize": false
  },
  {
   "id": "aab48de6-f0fe-4b2a-8dc1-de59612f74b2",
   "type": "",
   "Data": {
    "Line": 30,
    "Contest": "run",
    "Info": "run code"
   },
   "Columns": null,
   "PreventUserColumnResize": false
  },
  {
   "id": "cac9ff0b-bf83-4bb1-9635-71e907a09da2",
   "type": "",
   "Data": {
    "Line": 31,
    "Contest": "run",
    "Info": "run code"
   },
   "Columns": null,
   "PreventUserColumnResize": false
  },
  {
   "id": "426d855f-df02-433e-a24f-3f14e89db942",
   "type": "",
   "Data": {
    "Line": 32,
    "Contest": "run",
    "Info": "run code"
   },
   "Columns": null,
   "PreventUserColumnResize": false
  },
  {
   "id": "1ec0cbf7-cfdf-451f-9991-71d473546455",
   "type": "",
   "Data": {
    "Line": 33,
    "Contest": "run",
    "Info": "run code"
   },
   "Columns": null,
   "PreventUserColumnResize": false
  },
  {
   "id": "08d372f3-b9cc-4eef-8ae2-f0a414b47131",
   "type": "",
   "Data": {
    "Line": 34,
    "Contest": "run",
    "Info": "run code"
   },
   "Columns": null,
   "PreventUserColumnResize": false
  },
  {
   "id": "26fff711-e658-4381-b703-2b776a4ee591",
   "type": "",
   "Data": {
    "Line": 35,
    "Contest": "run",
    "Info": "run code"
   },
   "Columns": null,
   "PreventUserColumnResize": false
  },
  {
   "id": "af973d0e-0a8a-42a0-97da-c8d5d626c3b9",
   "type": "",
   "Data": {
    "Line": 36,
    "Contest": "run",
    "Info": "run code"
   },
   "Columns": null,
   "PreventUserColumnResize": false
  },
  {
   "id": "d84f3d0b-2bd0-4a8e-adcf-f31785fe6a10",
   "type": "",
   "Data": {
    "Line": 37,
    "Contest": "run",
    "Info": "run code"
   },
   "Columns": null,
   "PreventUserColumnResize": false
  },
  {
   "id": "f8efce31-6934-4e13-acfd-cc135bc1d681",
   "type": "",
   "Data": {
    "Line": 38,
    "Contest": "run",
    "Info": "run code"
   },
   "Columns": null,
   "PreventUserColumnResize": false
  },
  {
   "id": "8f249aff-ce4f-45d5-8289-2c9b440b1103",
   "type": "",
   "Data": {
    "Line": 39,
    "Contest": "run",
    "Info": "run code"
   },
   "Columns": null,
   "PreventUserColumnResize": false
  },
  {
   "id": "e9ef90ee-12fc-4575-8d0f-c6b0105c6df6",
   "type": "",
   "Data": {
    "Line": 40,
    "Contest": "run",
    "Info": "run code"
   },
   "Columns": null,
   "PreventUserColumnResize": false
  },
  {
   "id": "e38cee24-a64f-41cb-9cd1-ebfbe0e248a5",
   "type": "",
   "Data": {
    "Line": 41,
    "Contest": "run",
    "Info": "run code"
   },
   "Columns": null,
   "PreventUserColumnResize": false
  },
  {
   "id": "c95b5fa7-7f7a-485b-a4bc-81820d378ebb",
   "type": "",
   "Data": {
    "Line": 42,
    "Contest": "run",
    "Info": "run code"
   },
   "Columns": null,
   "PreventUserColumnResize": false
  },
  {
   "id": "a7541ee3-8c94-4764-9b54-f802882a170c",
   "type": "",
   "Data": {
    "Line": 43,
    "Contest": "run",
    "Info": "run code"
   },
   "Columns": null,
   "PreventUserColumnResize": false
  },
  {
   "id": "34fd7b30-adb9-4e50-b32d-f776b75187b2",
   "type": "",
   "Data": {
    "Line": 44,
    "Contest": "run",
    "Info": "run code"
   },
   "Columns": null,
   "PreventUserColumnResize": false
  },
  {
   "id": "7b98f9bf-01c2-4ae7-852c-0b600bef570c",
   "type": "",
   "Data": {
    "Line": 45,
    "Contest": "run",
    "Info": "run code"
   },
   "Columns": null,
   "PreventUserColumnResize": false
  },
  {
   "id": "4d662e02-1010-4d29-9a0c-eca7eddf8f72",
   "type": "",
   "Data": {
    "Line": 46,
    "Contest": "run",
    "Info": "run code"
   },
   "Columns": null,
   "PreventUserColumnResize": false
  },
  {
   "id": "62ae7b87-0b78-47ed-9164-b6eb4e80c186",
   "type": "",
   "Data": {
    "Line": 47,
    "Contest": "run",
    "Info": "run code"
   },
   "Columns": null,
   "PreventUserColumnResize": false
  },
  {
   "id": "1b0e05ca-4d41-4a7c-8b9b-a187ee7b7a53",
   "type": "",
   "Data": {
    "Line": 48,
    "Contest": "run",
    "Info": "run code"
   },
   "Columns": null,
   "PreventUserColumnResize": false
  },
  {
   "id": "8040afa2-1f0d-4b6d-99b5-55c0bd6086f7",
   "type": "",
   "Data": {
    "Line": 49,
    "Contest": "run",
    "Info": "run code"
   },
   "Columns": null,
   "PreventUserColumnResize": false
  },
  {
   "id": "477c46ba-4f54-49eb-b47e-3d992375d259",
   "type": "",
   "Data": {
    "Line": 50,
    "Contest": "run",
    "Info": "run code"
   },
   "Columns": null,
   "PreventUserColumnResize": false
  },
  {
   "id": "89f3ac34-90e8-4f53-95d4-697f9c9fff22",
   "type": "",
   "Data": {
    "Line": 51,
    "Contest": "run",
    "Info": "run code"
   },
   "Columns": null,
   "PreventUserColumnResize": false
  },
  {
   "id": "c99d93b3-a7f2-499e-8181-9d2d35202afc",
   "type": "",
   "Data": {
    "Line": 52,
    "Contest": "run",
    "Info": "run code"
   },
   "Columns": null,
   "PreventUserColumnResize": false
  },
  {
   "id": "eeba3a44-e04a-42a4-bd58-616d23f57ec2",
   "type": "",
   "Data": {
    "Line": 53,
    "Contest": "run",
    "Info": "run code"
   },
   "Columns": null,
   "PreventUserColumnResize": false
  },
  {
   "id": "b2ef7754-e8ef-49bb-9d68-61507b367768",
   "type": "",
   "Data": {
    "Line": 54,
    "Contest": "run",
    "Info": "run code"
   },
   "Columns": null,
   "PreventUserColumnResize": false
  },
  {
   "id": "17c3a4cb-9db7-4e4e-b862-089c7c269024",
   "type": "",
   "Data": {
    "Line": 55,
    "Contest": "run",
    "Info": "run code"
   },
   "Columns": null,
   "PreventUserColumnResize": false
  },
  {
   "id": "f25094b9-9c9b-4b31-84c6-bcbdac98b71f",
   "type": "",
   "Data": {
    "Line": 56,
    "Contest": "run",
    "Info": "run code"
   },
   "Columns": null,
   "PreventUserColumnResize": false
  },
  {
   "id": "4e9382e3-940e-4bf0-ab6b-454e4237abf7",
   "type": "",
   "Data": {
    "Line": 57,
    "Contest": "run",
    "Info": "run code"
   },
   "Columns": null,
   "PreventUserColumnResize": false
  },
  {
   "id": "e04c77d2-46f8-44eb-a141-d186fa5a7839",
   "type": "",
   "Data": {
    "Line": 58,
    "Contest": "run",
    "Info": "run code"
   },
   "Columns": null,
   "PreventUserColumnResize": false
  },
  {
   "id": "43333c91-1cdb-45ce-993e-963d7d8c6e92",
   "type": "",
   "Data": {
    "Line": 59,
    "Contest": "run",
    "Info": "run code"
   },
   "Columns": null,
   "PreventUserColumnResize": false
  },
  {
   "id": "d04f3cd1-5a8e-4fc2-8370-19e48fc97e15",
   "type": "",
   "Data": {
    "Line": 60,
    "Contest": "run",
    "Info": "run code"
   },
   "Columns": null,
   "PreventUserColumnResize": false
  },
  {
   "id": "80d1230e-5093-4b3f-bb0a-8b7b7efbc7aa",
   "type": "",
   "Data": {
    "Line": 61,
    "Contest": "run",
    "Info": "run code"
   },
   "Columns": null,
   "PreventUserColumnResize": false
  },
  {
   "id": "cd69a396-cec5-4022-8c5f-e47075807838",
   "type": "",
   "Data": {
    "Line": 62,
    "Contest": "run",
    "Info": "run code"
   },
   "Columns": null,
   "PreventUserColumnResize": false
  },
  {
   "id": "80103785-f71a-40cc-8642-0ed6b0476517",
   "type": "",
   "Data": {
    "Line": 63,
    "Contest": "run",
    "Info": "run code"
   },
   "Columns": null,
   "PreventUserColumnResize": false
  },
  {
   "id": "01df4aef-92bd-4b8b-a9a6-d88ffff65171",
   "type": "",
   "Data": {
    "Line": 64,
    "Contest": "run",
    "Info": "run code"
   },
   "Columns": null,
   "PreventUserColumnResize": false
  },
  {
   "id": "cfdd94e7-5bf1-4cd8-be57-6670ea525f95",
   "type": "",
   "Data": {
    "Line": 65,
    "Contest": "run",
    "Info": "run code"
   },
   "Columns": null,
   "PreventUserColumnResize": false
  },
  {
   "id": "a98c2c3f-d75f-417c-bcd8-52e7e0f7a280",
   "type": "",
   "Data": {
    "Line": 66,
    "Contest": "run",
    "Info": "run code"
   },
   "Columns": null,
   "PreventUserColumnResize": false
  },
  {
   "id": "46c8753a-104d-4f20-8984-3ad59af97d39",
   "type": "",
   "Data": {
    "Line": 67,
    "Contest": "run",
    "Info": "run code"
   },
   "Columns": null,
   "PreventUserColumnResize": false
  },
  {
   "id": "7d3e644d-7fee-4036-9bf4-1be7bfd2b036",
   "type": "",
   "Data": {
    "Line": 68,
    "Contest": "run",
    "Info": "run code"
   },
   "Columns": null,
   "PreventUserColumnResize": false
  },
  {
   "id": "fb4cdfb0-8bbd-4973-8de9-e2db4680961b",
   "type": "",
   "Data": {
    "Line": 69,
    "Contest": "run",
    "Info": "run code"
   },
   "Columns": null,
   "PreventUserColumnResize": false
  },
  {
   "id": "cfedb61e-1200-4f4e-8684-187311bd0924",
   "type": "",
   "Data": {
    "Line": 70,
    "Contest": "run",
    "Info": "run code"
   },
   "Columns": null,
   "PreventUserColumnResize": false
  },
  {
   "id": "c5f04dbf-e928-4eb5-930e-f0054697b536",
   "type": "",
   "Data": {
    "Line": 71,
    "Contest": "run",
    "Info": "run code"
   },
   "Columns": null,
   "PreventUserColumnResize": false
  },
  {
   "id": "a9f7b368-0044-4894-85d8-f330cf9344b4",
   "type": "",
   "Data": {
    "Line": 72,
    "Contest": "run",
    "Info": "run code"
   },
   "Columns": null,
   "PreventUserColumnResize": false
  },
  {
   "id": "28d863bc-b59f-49ee-a75d-b1a0050745dd",
   "type": "",
   "Data": {
    "Line": 73,
    "Contest": "run",
    "Info": "run code"
   },
   "Columns": null,
   "PreventUserColumnResize": false
  },
  {
   "id": "2428ffdc-fb28-496b-977f-828e35ddc78b",
   "type": "",
   "Data": {
    "Line": 74,
    "Contest": "run",
    "Info": "run code"
   },
   "Columns": null,
   "PreventUserColumnResize": false
  },
  {
   "id": "da12d35f-4d25-408b-bfc1-f0b49bae0088",
   "type": "",
   "Data": {
    "Line": 75,
    "Contest": "run",
    "Info": "run code"
   },
   "Columns": null,
   "PreventUserColumnResize": false
  },
  {
   "id": "f9d1cd7c-7e29-4a14-8587-edbd58841c04",
   "type": "",
   "Data": {
    "Line": 76,
    "Contest": "run",
    "Info": "run code"
   },
   "Columns": null,
   "PreventUserColumnResize": false
  },
  {
   "id": "70b49662-2c54-42e8-942d-d523c2033269",
   "type": "",
   "Data": {
    "Line": 77,
    "Contest": "run",
    "Info": "run code"
   },
   "Columns": null,
   "PreventUserColumnResize": false
  },
  {
   "id": "9e7727f5-efa4-4a21-9cea-1935f44ac7c6",
   "type": "",
   "Data": {
    "Line": 78,
    "Contest": "run",
    "Info": "run code"
   },
   "Columns": null,
   "PreventUserColumnResize": false
  },
  {
   "id": "9ce1def7-10a4-4022-a237-b55961a8f5cd",
   "type": "",
   "Data": {
    "Line": 79,
    "Contest": "run",
    "Info": "run code"
   },
   "Columns": null,
   "PreventUserColumnResize": false
  },
  {
   "id": "d6f4fc30-2c76-499a-992b-f2a971d0320e",
   "type": "",
   "Data": {
    "Line": 80,
    "Contest": "run",
    "Info": "run code"
   },
   "Columns": null,
   "PreventUserColumnResize": false
  },
  {
   "id": "9608b694-4f7e-4201-8b11-70137985f47f",
   "type": "",
   "Data": {
    "Line": 81,
    "Contest": "run",
    "Info": "run code"
   },
   "Columns": null,
   "PreventUserColumnResize": false
  },
  {
   "id": "718998a9-2626-4dac-8b0e-0d0d5770da9e",
   "type": "",
   "Data": {
    "Line": 82,
    "Contest": "run",
    "Info": "run code"
   },
   "Columns": null,
   "PreventUserColumnResize": false
  },
  {
   "id": "188cace5-d6d6-4a96-9adc-ef7f99313774",
   "type": "",
   "Data": {
    "Line": 83,
    "Contest": "run",
    "Info": "run code"
   },
   "Columns": null,
   "PreventUserColumnResize": false
  },
  {
   "id": "c8d502a0-1858-473c-baff-aba353d6ce95",
   "type": "",
   "Data": {
    "Line": 84,
    "Contest": "run",
    "Info": "run code"
   },
   "Columns": null,
   "PreventUserColumnResize": false
  },
  {
   "id": "861aa7a3-7e85-457a-927b-21510b184a30",
   "type": "",
   "Data": {
    "Line": 85,
    "Contest": "run",
    "Info": "run code"
   },
   "Columns": null,
   "PreventUserColumnResize": false
  },
  {
   "id": "258a6402-e821-4d0b-afa1-fa0a25b06c71",
   "type": "",
   "Data": {
    "Line": 86,
    "Contest": "run",
    "Info": "run code"
   },
   "Columns": null,
   "PreventUserColumnResize": false
  },
  {
   "id": "f50ca3b1-9075-4eab-b106-2f2926c3677e",
   "type": "",
   "Data": {
    "Line": 87,
    "Contest": "run",
    "Info": "run code"
   },
   "Columns": null,
   "PreventUserColumnResize": false
  },
  {
   "id": "0a24bfdd-2b20-4e3a-9fb7-62f8635df75f",
   "type": "",
   "Data": {
    "Line": 88,
    "Contest": "run",
    "Info": "run code"
   },
   "Columns": null,
   "PreventUserColumnResize": false
  },
  {
   "id": "21b3a9f1-0d8a-42e7-9be2-2d5adb1bf615",
   "type": "",
   "Data": {
    "Line": 89,
    "Contest": "run",
    "Info": "run code"
   },
   "Columns": null,
   "PreventUserColumnResize": false
  },
  {
   "id": "11f64f40-bfe6-4dfa-a983-2d0216ab27bf",
   "type": "",
   "Data": {
    "Line": 90,
    "Contest": "run",
    "Info": "run code"
   },
   "Columns": null,
   "PreventUserColumnResize": false
  },
  {
   "id": "c0edbe94-478d-4602-a38e-726c8b4dbf92",
   "type": "",
   "Data": {
    "Line": 91,
    "Contest": "run",
    "Info": "run code"
   },
   "Columns": null,
   "PreventUserColumnResize": false
  },
  {
   "id": "52a6dc5e-f375-4c64-90d7-840d4e5b6916",
   "type": "",
   "Data": {
    "Line": 92,
    "Contest": "run",
    "Info": "run code"
   },
   "Columns": null,
   "PreventUserColumnResize": false
  },
  {
   "id": "0a65240d-c302-4b18-90e1-5b7ddbf58a43",
   "type": "",
   "Data": {
    "Line": 93,
    "Contest": "run",
    "Info": "run code"
   },
   "Columns": null,
   "PreventUserColumnResize": false
  },
  {
   "id": "e5229d74-9afb-4358-8d21-52f1cb0d54ed",
   "type": "",
   "Data": {
    "Line": 94,
    "Contest": "run",
    "Info": "run code"
   },
   "Columns": null,
   "PreventUserColumnResize": false
  },
  {
   "id": "709540b2-d80b-4655-83b8-8f296e8de8cb",
   "type": "",
   "Data": {
    "Line": 95,
    "Contest": "run",
    "Info": "run code"
   },
   "Columns": null,
   "PreventUserColumnResize": false
  },
  {
   "id": "b946b915-c28b-4ceb-b10e-351b57351c7d",
   "type": "",
   "Data": {
    "Line": 96,
    "Contest": "run",
    "Info": "run code"
   },
   "Columns": null,
   "PreventUserColumnResize": false
  },
  {
   "id": "d15db205-216c-4a74-83f1-9e9c6003aa9d",
   "type": "",
   "Data": {
    "Line": 97,
    "Contest": "run",
    "Info": "run code"
   },
   "Columns": null,
   "PreventUserColumnResize": false
  },
  {
   "id": "9da87193-ec4e-43b6-b0b9-339f4a51ebac",
   "type": "",
   "Data": {
    "Line": 98,
    "Contest": "run",
    "Info": "run code"
   },
   "Columns": null,
   "PreventUserColumnResize": false
  },
  {
   "id": "52b8045d-c8bc-460e-b8af-fa2a48778fb7",
   "type": "",
   "Data": {
    "Line": 99,
    "Contest": "run",
    "Info": "run code"
   },
   "Columns": null,
   "PreventUserColumnResize": false
  }
 ],
 "Columns": [
  {
   "ID": 0,
   "Current": 44,
   "Minimum": 34.072266,
   "Maximum": 10000,
   "AutoMinimum": 0,
   "AutoMaximum": 0,
   "Cell": "Line"
  },
  {
   "ID": 1,
   "Current": 56.603516,
   "Minimum": 56.603516,
   "Maximum": 10000,
   "AutoMinimum": 0,
   "AutoMaximum": 0,
   "Cell": "Contest"
  },
  {
   "ID": 2,
   "Current": 63,
   "Minimum": 32.376953,
   "Maximum": 10000,
   "AutoMinimum": 0,
   "AutoMaximum": 0,
   "Cell": "Info"
  }
 ],
 "PreventUserColumnResize": false
}